boursocrawling/__init__.py
boursocrawling/forecasts.py
boursocrawling/stockdata.py
boursocrawling-1.1.0.dist-info/METADATA
boursocrawling-1.1.0.dist-info/WHEEL
boursocrawling-1.1.0.dist-info/top_level.txt
boursocrawling-1.1.0.dist-info/RECORD
